odoo8_addon_scheduler_error_mailer-8.0.1.0.0.99.dev16-nspkg.pth
odoo_addons/scheduler_error_mailer/__init__.py
odoo_addons/scheduler_error_mailer/__openerp__.py
odoo_addons/scheduler_error_mailer/ir_cron.py
odoo_addons/scheduler_error_mailer/ir_cron.xml
odoo_addons/scheduler_error_mailer/ir_cron_demo.xml
odoo_addons/scheduler_error_mailer/ir_cron_email_tpl.xml
odoo_addons/scheduler_error_mailer/i18n/ca.po
odoo_addons/scheduler_error_mailer/i18n/de.po
odoo_addons/scheduler_error_mailer/i18n/es.po
odoo_addons/scheduler_error_mailer/i18n/fr.po
odoo_addons/scheduler_error_mailer/i18n/it.po
odoo_addons/scheduler_error_mailer/i18n/pt_BR.po
odoo_addons/scheduler_error_mailer/i18n/scheduler_error_mailer.pot
odoo_addons/scheduler_error_mailer/i18n/sl.po
odoo_addons/scheduler_error_mailer/i18n/tr.po
odoo_addons/scheduler_error_mailer/images/scheduler_error_mailer.jpg
odoo_addons/scheduler_error_mailer/static/description/icon.png
odoo8_addon_scheduler_error_mailer-8.0.1.0.0.99.dev16.dist-info/METADATA
odoo8_addon_scheduler_error_mailer-8.0.1.0.0.99.dev16.dist-info/WHEEL
odoo8_addon_scheduler_error_mailer-8.0.1.0.0.99.dev16.dist-info/namespace_packages.txt
odoo8_addon_scheduler_error_mailer-8.0.1.0.0.99.dev16.dist-info/top_level.txt
odoo8_addon_scheduler_error_mailer-8.0.1.0.0.99.dev16.dist-info/RECORD
